patterpunk/__init__.py
patterpunk/config.py
patterpunk/logger.py
patterpunk/config/__init__.py
patterpunk/config/defaults.py
patterpunk/config/providers/__init__.py
patterpunk/config/providers/anthropic.py
patterpunk/config/providers/azure_openai.py
patterpunk/config/providers/bedrock.py
patterpunk/config/providers/google.py
patterpunk/config/providers/ollama.py
patterpunk/config/providers/openai.py
patterpunk/lib/__init__.py
patterpunk/lib/extract_json.py
patterpunk/lib/function_to_tool.py
patterpunk/lib/structured_output.py
patterpunk/lib/function_to_tool/__init__.py
patterpunk/lib/function_to_tool/cleaning.py
patterpunk/lib/function_to_tool/converter.py
patterpunk/lib/function_to_tool/inspection.py
patterpunk/lib/function_to_tool/schema.py
patterpunk/lib/function_to_tool/docstring/__init__.py
patterpunk/lib/function_to_tool/docstring/advanced.py
patterpunk/lib/function_to_tool/docstring/parser.py
patterpunk/lib/function_to_tool/docstring/simple.py
patterpunk/lib/mcp/__init__.py
patterpunk/lib/mcp/client.py
patterpunk/lib/mcp/exceptions.py
patterpunk/lib/mcp/server_config.py
patterpunk/lib/mcp/tool_converter.py
patterpunk/llm/__init__.py
patterpunk/llm/agent.py
patterpunk/llm/chain.py
patterpunk/llm/defaults.py
patterpunk/llm/output_types.py
patterpunk/llm/streaming.py
patterpunk/llm/thinking.py
patterpunk/llm/tool_types.py
patterpunk/llm/types.py
patterpunk/llm/utils.py
patterpunk/llm/chat/__init__.py
patterpunk/llm/chat/core.py
patterpunk/llm/chat/exceptions.py
patterpunk/llm/chat/structured_output.py
patterpunk/llm/chat/tools.py
patterpunk/llm/chunks/__init__.py
patterpunk/llm/chunks/cache.py
patterpunk/llm/chunks/multimodal.py
patterpunk/llm/chunks/text.py
patterpunk/llm/messages/__init__.py
patterpunk/llm/messages/assistant.py
patterpunk/llm/messages/base.py
patterpunk/llm/messages/cache.py
patterpunk/llm/messages/exceptions.py
patterpunk/llm/messages/roles.py
patterpunk/llm/messages/serialization.py
patterpunk/llm/messages/structured_output.py
patterpunk-1.1.1.dist-info/METADATA
patterpunk-1.1.1.dist-info/WHEEL
patterpunk-1.1.1.dist-info/top_level.txt
patterpunk-1.1.1.dist-info/RECORD
